bq/release.py
bq/service.py
bq/exceptions.py
bq/__init__.py
bq/setup/bundles.py
bq/setup/bisque_setup.py
bq/setup/__init__.py
bq/setup/create_config.py
bq/setup/templates/__init__.py
bq/setup/templates/config/shell.ini.default
bq/setup/templates/config/runtime-bisque.default
bq/setup/templates/config/EXTERNAL_FILES
bq/setup/templates/config/registration.cfg.default
bq/setup/templates/config/engine.cfg.default
bq/setup/templates/config/who.ini.default
bq/setup/templates/config/engine.ini_templ
bq/setup/templates/config/preferences.xml.default
bq/setup/templates/config/server.ini.default
bq/setup/templates/config/who.engine.default
bq/setup/templates/config/alembic.ini.default
bq/setup/templates/config/uwsgi.cfg.default
bq/setup/templates/config/site.cfg.default
bq/setup/templates/config/templates/python_launcher.tmpl
bq/setup/templates/config/templates/condor_submit.tmpl
bq/setup/templates/config/templates/matlab_launcher.tmpl
bq/setup/templates/config/templates/condor_dag.tmpl
bq/setup/templates/config/templates/condor_submit_shared.tmpl
bq/setup/templates/config/templates/matlab_launcher_win.tmpl
bq/setup/templates/config/templates/condor_dag_conf.tmpl
bq/util/mkdir.py
bq/util/read_write_locks.py
bq/util/xmldict.py
bq/util/urlnorm.py
bq/util/compat.py
bq/util/registration.py
bq/util/security.py
bq/util/diskusage.py
bq/util/locks.py
bq/util/hash.py
bq/util/memoize.py
bq/util/dotnested.py
bq/util/abort.py
bq/util/fileapp.py
bq/util/urlutil.py
bq/util/configfile.py
bq/util/samehost.py
bq/util/LinesmanProfiler.py
bq/util/paths.py
bq/util/bqrender.py
bq/util/timer.py
bq/util/baseconvert.py
bq/util/bix2db.py
bq/util/sizeoffmt.py
bq/util/XFile.py
bq/util/__init__.py
bq/util/s3_handler.py
bq/util/fakerequestenv.py
bq/util/etreerender.py
bq/util/converters.py
bq/util/bisque_types.py
bq/util/permission.py
bq/util/wait_pid.py
bq/util/thread_pool.py
bq/util/io_misc.py
bq/util/routes.py
bq/util/request.py
bisque_base-0.6a4.dist-info/entry_points.txt
bisque_base-0.6a4.dist-info/top_level.txt
bisque_base-0.6a4.dist-info/WHEEL
bisque_base-0.6a4.dist-info/DESCRIPTION.rst
bisque_base-0.6a4.dist-info/RECORD
bisque_base-0.6a4.dist-info/METADATA
bisque_base-0.6a4.dist-info/metadata.json
